pd3/regfile.sv
module regfile(
		input [4:0] wr_num, input [31:0] wr_data, input wr_en,
		input [4:0] rd0_num, output [31:0] rd0_data,
		input [4:0] rd1_num, output [31:0] rd1_data,
		input clk);

    reg[31:0] data [1:31]; // general-purpose registers r1-r31 (r0===0)

	always @(posedge clk)
        if(wr_en && wr_num!=0) data[wr_num] <= wr_data;
   	assign rd0_data = (rd0_num!=0) ? data[rd0_num] : 32'h00000000;
   	assign rd1_data = (rd1_num!=0) ? data[rd1_num] : 32'h00000000;

endmodule

PD4/mips.sv
module mips(input clk, reset,
					input logic [31:0] instr_in, data_in,
					output logic [31:0] instr_addr, data_addr, data_out, 
					output logic data_rd_wr);
	parameter [31:0] pc_init = 32'h80020000;
    parameter [31:0] sp_init = 32'h80120000; 
	parameter [31:0] ra_init = 32'h00000000;
	
	logic 		 alu_en,
				 sign_extend_en,
				 EX_reg_wr_en,
				 EX_wb_en,
				 EX_mem_en,
				 data_rw_en,
				 ME_wb_en,
				 ME_data_rw_en,
				 ME_reg_wr_en,
				 ME_mem_en,
				 WB_wb_en,
				 WB_reg_wr_en;			 
	
	
			   
	
	logic [4:0]	 EX_wr_sel,
				 ME_wr_sel,
				 WB_wr_sel,
				 rd_sel,
				 rs_sel,
				 alu_op;
	
	logic [31:0] pc; 			// program counter
	logic [31:0] /*IF_IS_IMPLIED*/ ID_instr_reg, EX_instr_reg, ME_instr_reg, WB_instr_reg;
	//Instruction propagation	
	logic [31:0] rs, 			// register output 2
				 rd, 			// destination register
				 alu_out,		// alu output reg
				 EX_wr_reg,
				 ME_wr_reg,
				 WB_wr_reg_data;		// write to register register
	 
	regfile regs(.wr_num(WB_wr_sel), .wr_data(WB_wr_reg_data), .wr_en(WB_reg_wr_en),
		.rd0_num(rd_sel), .rd0_data(rd),
		.rd1_num(rs_sel), .rd1_data(rs),
		.clk(clk));
	
	logic IF_en,ID_en, EX_en, ME_en, WB_en;
	
	initial begin
		IF_en = 1'b0;
		ID_en = 1'b0;
		EX_en = 1'b0;
		ME_en = 1'b0;
		WB_en = 1'b0;
		
		data_addr 	<= sp_init;
		pc 			<= pc_init;
		instr_addr  <= pc_init;
		data_rw_en   <= 1'b1;
		data_rd_wr	<= 1'b1;
		alu_en		<= 1'b0;
		EX_wb_en	<= 1'b0;
		ME_wb_en	<= 1'b0;
		WB_wb_en    <= 1'b0;
		EX_mem_en 	<= 1'b0;
		ME_mem_en 	<= 1'b0;
		alu_out		<= 32'h0;
		alu_op 		<= 5'b0;
		
		WB_wr_sel 		<= 5'h1D; //sp_init = R29
		WB_wr_reg_data		<= sp_init;
		WB_reg_wr_en    <= 1'b1;
		ME_reg_wr_en	<= 1'b0;
		EX_reg_wr_en	<= 1'b0;
		
		//#10 wr_sel 		<= 5'h1F; //ra_init = R31
		//wr_reg		<= ra_init;
		/*#90 pc <= 32'h80020018;
		#10	pc <= 32'h8002001c;
		#10	pc <= 32'h80020020;
		#10	pc <= 32'h80020024;
		#20	pc <= 32'h8002002c;
		#40	pc <= 32'h8002003c;
		#30 pc <= 32'h0;*/
	end
	
	always @ (reset) begin
	    if(reset) begin
	    	IF_en <= 1'b0;
			ID_en <= 1'b0;
			EX_en <= 1'b0;
			ME_en <= 1'b0;
			WB_en <= 1'b0;
			WB_reg_wr_en    <= 1'b1;

		end else begin
			IF_en <= 1'b1;
			WB_wr_sel 		<= 5'h1D; //sp_init = R29
			WB_wr_reg_data		<= sp_init;
			WB_reg_wr_en    <= 1'b1;

		end
	end
	
	always @ (pc)
	begin
		if(~reset) begin
			instr_addr <= pc;
			IF_en = 1'b1;
		end
	end
	
	always @ (posedge clk)
	begin : IF
		if(IF_en) begin
			ID_instr_reg <= instr_in;
			ID_en <= 1'b1;
		end else begin
			WB_wr_sel <= 5'h1F; //ra_init = R31
			WB_wr_reg_data <= ra_init;
			WB_reg_wr_en <= 1'b1;
		end
	end //IF
	
	always @ (posedge clk) 
	begin: ID
		if(ID_en) begin
		//decode current_instr to instruction (+ immediate)
		//instructions we will need: 	
		//addiu addu jr li lw move nop sw
		//pages refer to pdf page # in MIPS ISA
		EX_instr_reg <= ID_instr_reg;
		case(ID_instr_reg[31:26])
			6'b001001: begin
				//ADDIU rt, rs, immediate
				//add immediate unsigned (pg 47)
				//[31:26]: 001001
				// [0010 01][11 101][1 1101]
				EX_wr_sel <= ID_instr_reg[20:16]; //store result here (rt)
				rs_sel <= ID_instr_reg[25:21]; //operand 1, rs 
				sign_extend_en <= 1'b1; //operand 2, immediate, sets alu_2
				alu_en <= 1'b1;
				alu_op <= 5'b00001;
				EX_wb_en <= 1'b1;
				EX_mem_en <= 1'b0;
				alu_op <= 5'b00001;
			end
			6'b100011: begin
				//LW rt, offset(base)
				//load word from memory (pg 171) 
				//[31:26]: 100011
				EX_wr_sel <= ID_instr_reg[20:16]; // store from mem to this reg (rt)
				rs_sel = ID_instr_reg[25:21]; // base addr
				sign_extend_en <= 1'b1; //sets alu_2 with offset
				alu_en <= 1'b1;
				alu_op <= 5'b00001;
				EX_wb_en <= 1'b1;
				EX_mem_en <= 1'b1;
			end
			//NOTE: LW and SW seem similar so far - change to common stage? only diff is 10(0/1)011
			6'b101011: begin
				//SW, rt, offset(base)
				//store word from rt to memory[base+offset] (pg 280)
			    //address error exception if last two bits != 00
				//[31:26]: 101011
				EX_wr_sel <= ID_instr_reg[20:16]; //writeback setup
				rs_sel <= ID_instr_reg[25:21]; //base address
				rd_sel <= ID_instr_reg[20:16]; //source word
				sign_extend_en <= 1'b1; //sets alu_2 with immediate
				alu_en <= 1'b1;
				alu_op <= 5'b00001;
				EX_wb_en <= 1'b0;
				EX_mem_en <= 1'b1;
			end
			6'b000100 : begin
				//BEQ
				//  rs [25:21] rt [20:16] offset [15:0]
				//I: target_offset ← sign_extend(offset || 02)
				//	condition ← (GPR[rs] = GPR[rt])
				//I+1: if condition then
				//		PC ← PC + target_offset
				//	 endif
				rs_sel = ID_instr_reg[25:21];
				rd_sel = ID_instr_reg[20:16];
				if (rs == rd) begin
					alu_en = 1'b1;
					sign_extend_en = 1'b1;
					alu_op <= 5'b10000;
				end else begin
					alu_en = 1'b0;
					sign_extend_en = 1'b0;
					alu_op <= 5'b00000;
				end
				EX_wb_en <= 1'b0;
				EX_mem_en <= 1'b0;
			end
			6'b000000 : begin  //SPECIAL
				case(instr_in[5:0]) 
					6'b100011 : begin //SUBU
						//SUBU sub unsigned
						// 000000 rs [25:21] rt [20:16] rd [15:11] 00000 100011 (SUBU)
						// rd <- rs - rt
						rs_sel <= ID_instr_reg[25:21]; //op2
						rd_sel <= ID_instr_reg[20:16]; //op1
						EX_wr_sel <= ID_instr_reg[15:11]; //destination
						alu_en <= 1'b1;
					    alu_op <= 5'b00010;
						sign_extend_en <= 1'b0;
						EX_wb_en <= 1'b1;
						EX_mem_en <= 1'b0;
					end
					6'b001000 : begin
						//JR rs
						//jump register, set PC to rs (pg 155) 
						//[31:26]: 000000 & [5:0]: 0010000
						rs_sel = ID_instr_reg[25:21];
						pc = rs;
						alu_en <= 1'b0;
						alu_op <= 5'b00000;
						EX_wb_en <= 1'b0;
						EX_mem_en <= 1'b0;
					end
					6'b000000 : begin
						//NOP
						//not an op, actually SLL r0, r0, 0 (pg 226) do we need to actually implement this way?
						//[31:26]: 000000 & SLL [5:0]=000000
						//r0 <= r0 << 1'b0;
						//SLL
						// 000000 00000 rt [20:16] rd [15:11] sa [10:6] 000000
						//rd <- rt << sa
						EX_wr_sel = ID_instr_reg[15:11];
						rs_sel <= ID_instr_reg[20:16];
						alu_en <= 1'b0;
						alu_op <= 5'b01000;
						EX_mem_en <= 1'b0;
						EX_wb_en <= 1'b0;
					end
				endcase
			end
		endcase
		EX_en <= 1'b1;
		end
	end // ID
	
	always @ (posedge clk)
	begin: EX
		if(EX_en) begin
			ME_wb_en <= EX_wb_en;
			ME_mem_en <= EX_mem_en;
			ME_reg_wr_en <= EX_reg_wr_en;
			ME_wr_sel <= EX_instr_reg[20:16];
			ME_instr_reg <= EX_instr_reg;
			ME_en <= 1'b1;
			//execute arithmetic and instruction, eg. address = base + offset
			//run if alu_en is set
			//adds alu_1 and alu_2
			//output to alu_out
			if(alu_en == 1'b1) begin
				case(alu_op)
					5'b01000: begin //SLL
						alu_out <= rs << EX_instr_reg[10:6];
						ME_wr_reg <= rs << EX_instr_reg[10:6];
					end
					5'b00010: begin //SUBU
						alu_out <= rs - rd;
						ME_wr_reg <= rs - rd;
					end
					5'b00001: begin //ADDIU
						if(sign_extend_en) begin
							if(EX_instr_reg[15]) begin
								alu_out  = rs + { 16'hffff, EX_instr_reg[15:0]};
								data_out = rd;
								if (~EX_mem_en) begin
									ME_wr_reg <= rs + { 16'hffff, EX_instr_reg[15:0]};
								end else begin
									ME_wr_reg <= rd;
								end
							end else begin
								alu_out = rs + { 16'h0000, EX_instr_reg[15:0]};
								data_out = rd;
								if (~EX_mem_en) begin
									ME_wr_reg <= rs + { 16'h0000, EX_instr_reg[15:0]};
								end else begin
									ME_wr_reg <= rd;
								end
							end
							if (EX_mem_en) begin
								if(EX_instr_reg[29]) begin //TODO: Add write flag to avoid holding this reg
									data_addr = alu_out;
									data_rd_wr <= 1'b0;
								end else begin
									data_addr = alu_out;
									data_rd_wr <= 1'b1;
								end
							end else begin
								data_rd_wr <= 1'b1;
							end
						end else begin
							alu_out <= rs + rd;
							ME_wr_reg <= rs +rd;
						end
					end
					5'b10000 : begin //BRANCH OFFSET
						if(EX_instr_reg[15]) begin //Sign Extend should always be '1' don't explicitally check
							pc <= pc + {12'hfff, 2'b11, EX_instr_reg[15:0], 2'b00};
						end else begin
							pc <= pc + {12'h000, 2'b00, EX_instr_reg[15:0], 2'b00};
						end 
					end
				endcase
			end
			pc <= pc + 4;//increment PC after done with instr_in

		end
	end //EX
		
	always @ (posedge clk)
	begin: ME
		if(ME_en) begin
		 	WB_instr_reg <= ME_instr_reg;
		 	WB_wb_en <= ME_wb_en;
		 	WB_wr_sel <= ME_wr_sel;
		 	if(ME_mem_en) begin
				if(ME_instr_reg[29]) begin //TODO: Add write flag to avoid holding this reg
					WB_wb_en <= 1'b1;
					WB_wr_reg_data <= ME_wr_reg;
				end else begin
					WB_wb_en <= 1'b0;
					WB_wr_reg_data = data_in;
				end
			end else begin
				WB_wr_reg_data <= ME_wr_reg;
				WB_en <= 1'b1;
			end
		 	
		end
	end // ME

	always @ (posedge clk)
	begin: WB
		if(WB_en) begin
			if(WB_wb_en) begin
				WB_reg_wr_en <= 1'b1;
			end else begin
				WB_reg_wr_en <= 1'b0;
			end
		end
	end // WB

	
endmodule

main_memory.sv
module memory(input clk,
					input logic [31:0] addr, data_in,
					output logic [31:0] data_out,
					input logic [1:0] access_size,
					input logic rd_wr,
					output logic busy,
					input logic enable);
	parameter benchmark = "whatever.x";
    parameter depth = 2**20; // =1 MB
    
	reg[0:31] mem [depth-1: 0];
	logic [3:0] word_counter; //Rolling bit counter to detect offest/ which word is next to be read for multi word reads
	logic [4:0] next_word_counter;
	logic [1:0] byte_offset;
	logic [31:0] mem_index; // Offset address for next block of bytes in multi word reads
	logic [31:0] base_address; // corrected address removes the 8002xxxx from MIPS compiled hexadecimal
	
	initial begin
		$readmemh(benchmark, mem);
		busy = 0;
		byte_offset = 0;
		word_counter = 5'd0;
		byte_offset = addr[1:0];
		set_mem_index(addr);
		base_address = 32'b0;
	end
	
	always @ (enable, access_size, addr, rd_wr) begin
		if(enable && rd_wr) begin
			byte_offset = addr[1:0];
			set_mem_index(addr); 
			word_counter = 4'h0;
			read_data(mem_index, byte_offset, 4'd0);
		end
	end

	task set_mem_index(input [31:0] address);
	begin
		mem_index = addr ^ 32'h80020000; // Clear the base address generated by MIPS compiler
		mem_index = mem_index - byte_offset;
		mem_index = mem_index >> 2; // Takes the Floor (integer division) 
	end
	endtask
	
	always @ (posedge clk)
	begin : READ

		if(enable && rd_wr) begin
				// Read operations
				case(access_size)
					2'b00 : begin	// 4 Byte Read (Word)
						read_data(mem_index, byte_offset, 4'h0);
						word_counter = 4'h0;
					end
					2'b01 : begin	// 16 bytes (4 Words) 
						busy = 1;
						
						read_data(mem_index, byte_offset, word_counter + 5'd1);
						word_counter = word_counter + 5'd1;

						// reset word counter if completed read
						if(word_counter == 4'h3) begin
							word_counter = 4'h0;
							busy = 0;
							set_mem_index(addr);
						end
					end
					2'b10: begin	// 32 Bytes (8 Words)
						busy = 1;

						read_data(mem_index, byte_offset, word_counter + 5'd1);
						word_counter = word_counter + 5'd1;

						// reset word counter if completed read
						if(word_counter == 4'h7) begin
							word_counter = 4'h0;
							busy = 0;
							set_mem_index(addr);
						end
					end
					2'b11: begin
						// 64 Bytes (16 Words)
						busy = 1;
					    read_data(mem_index, byte_offset, word_counter + 5'd1);
						word_counter = word_counter + 5'd1;

						// reset word counter if completed read
						if(word_counter == 4'hf) begin
							word_counter = 4'h0;
							busy = 0;
							set_mem_index(addr);
						end
					end
					endcase
		end
	end // clock
	
	always @ (posedge clk) 
	begin : WRITE
		if(enable && ~rd_wr) begin	
			write_data(byte_offset);
		end
	end
	

	task read_data(input logic [31:0] address , input logic[1:0] byte_offset, logic[3:0] word_counter);
	begin
		case(byte_offset)
			2'h0: begin
				data_out = mem[address + word_counter];
			end
			2'h1: begin
				data_out = {mem[address + word_counter][8:31],  mem[address + word_counter + 1][0:7]};
			end
			2'h2: begin
				data_out = {mem[address + word_counter][16:31],  mem[address + word_counter + 1][0:15]};
			end
			2'h3: begin
				data_out = {mem[address + word_counter][24:31],  mem[address + word_counter + 1][0:23]};
			end
		endcase
	end
	endtask

	task write_data(input logic[1:0] byte_offset);
	begin
		case(byte_offset)
		2'h0: begin
			//Default Word write
			mem[mem_index] = data_in;
		end
		2'h1: begin // Fills 1,2,3 + 4
			mem[mem_index] = {mem[mem_index][0:7],data_in[31:8]};
			mem[mem_index + 1] = {data_in[7:0], mem[mem_index][8:31]};
		end
		2'h2: begin	// Fills 2,3, + 4,5
			mem[mem_index] = {mem[mem_index][0:15],data_in[31:16]};
			mem[mem_index + 1] = {data_in[15:0], mem[mem_index][16:31]};
		end
		2'h3: begin // Fills 3 + 4,5,6
			mem[mem_index] = {mem[mem_index][0:23],data_in[31:24]};
			mem[mem_index + 1] = {data_in[23:0], mem[mem_index][24:31]};
		end
		endcase
	end
	endtask

endmodule

PD4/pd4_tb.sv
// pipelined but no forwarding or stalling required
// expected output is found in test.out
module tb_test;
	logic clk;
	logic reset;

	parameter benchmark = "test.x";
	parameter mem_depth = 2**20;
	parameter [31:0] mem_start = 32'h80020000;

	// instruction memory
	logic im_rw = 1;
	logic [31:0] im_addr, im_dout;
	logic [1:0] im_sz = 0;
    memory #(.benchmark(benchmark), .depth(mem_depth)) imem(.clk(clk),
		.addr(im_addr), .data_out(im_dout),
		.access_size(im_sz), .rd_wr(im_rw), .enable(~reset));

	// data memory
	logic dm_rw;
	logic [31:0] dm_addr, dm_din, dm_dout;
	logic [1:0] dm_sz = 0;
    memory #(.benchmark(benchmark), .depth(mem_depth)) dmem(.clk(clk),
		.addr(dm_addr), .data_in(dm_din), .data_out(dm_dout),
		.access_size(dm_sz), .rd_wr(dm_rw), .enable(~reset));

	mips #(.pc_init(mem_start), .sp_init(mem_start+mem_depth), .ra_init(0))
		proc(.clk(clk), .reset(reset),
		.instr_addr(im_addr), .instr_in(im_dout),
		.data_addr(dm_addr), .data_in(dm_dout), .data_out(dm_din),
		.data_rd_wr(dm_rw));
 
    initial begin
        clk = 1; forever #5 clk = ~clk;
    end

    initial begin
        reset <= 1;
		#10 reset <= 0;

		wait(im_addr==32'h80020018)
   				$display("time %3d, v0 %0d", $time, tb_test.proc.regs.data[2]);
		wait(im_addr==32'h8002001c)
   				$display("time %3d, s0 %0d", $time, tb_test.proc.regs.data[16]);
		wait(im_addr==32'h80020020)
   				$display("time %3d, s1 %0d", $time, tb_test.proc.regs.data[17]);
		wait(im_addr==32'h80020024)
   				$display("time %3d, s2 %0d", $time, tb_test.proc.regs.data[18]);
		wait(im_addr==32'h8002002c)
   				$display("time %3d, v1 %0d", $time, tb_test.proc.regs.data[3]);
		wait(im_addr==32'h8002003c)
   				$display("time %3d, v0 %0d", $time, tb_test.proc.regs.data[2]);
   		$monitor("time %3d, pc %8h", $time, im_addr);

		wait(im_addr==0)
			#1 $finish; //$finish if using iverilog
    end

    initial $dumpvars(0, tb_test); // for iverilog+gtkwave

endmodule

PD4/dump.vcd
$date
	Thu Jul  7 02:30:09 2016
$end
$version
	Icarus Verilog
$end
$timescale
	1s
$end
$scope module tb_test $end
$var wire 32 ! im_dout [31:0] $end
$var wire 32 " im_addr [31:0] $end
$var wire 1 # dm_rw $end
$var wire 32 $ dm_dout [31:0] $end
$var wire 32 % dm_din [31:0] $end
$var wire 32 & dm_addr [31:0] $end
$var reg 1 ' clk $end
$var reg 2 ( dm_sz [1:0] $end
$var reg 1 ) im_rw $end
$var reg 2 * im_sz [1:0] $end
$var reg 1 + reset $end
$scope module dmem $end
$var wire 2 , access_size [1:0] $end
$var wire 1 ' clk $end
$var wire 1 - enable $end
$var wire 1 # rd_wr $end
$var wire 32 . data_in [31:0] $end
$var wire 32 / addr [31:0] $end
$var reg 32 0 base_address [31:0] $end
$var reg 1 1 busy $end
$var reg 2 2 byte_offset [1:0] $end
$var reg 32 3 data_out [31:0] $end
$var reg 32 4 mem_index [31:0] $end
$var reg 4 5 word_counter [3:0] $end
$scope begin READ $end
$upscope $end
$scope begin WRITE $end
$upscope $end
$scope task read_data $end
$var reg 32 6 address [31:0] $end
$var reg 2 7 byte_offset [1:0] $end
$var reg 4 8 word_counter [3:0] $end
$upscope $end
$scope task set_mem_index $end
$var reg 32 9 address [31:0] $end
$upscope $end
$scope task write_data $end
$var reg 2 : byte_offset [1:0] $end
$upscope $end
$upscope $end
$scope module imem $end
$var wire 2 ; access_size [1:0] $end
$var wire 1 ' clk $end
$var wire 32 < data_in [31:0] $end
$var wire 1 = enable $end
$var wire 1 ) rd_wr $end
$var wire 32 > addr [31:0] $end
$var reg 32 ? base_address [31:0] $end
$var reg 1 @ busy $end
$var reg 2 A byte_offset [1:0] $end
$var reg 32 B data_out [31:0] $end
$var reg 32 C mem_index [31:0] $end
$var reg 4 D word_counter [3:0] $end
$scope begin READ $end
$upscope $end
$scope begin WRITE $end
$upscope $end
$scope task read_data $end
$var reg 32 E address [31:0] $end
$var reg 2 F byte_offset [1:0] $end
$var reg 4 G word_counter [3:0] $end
$upscope $end
$scope task set_mem_index $end
$var reg 32 H address [31:0] $end
$upscope $end
$scope task write_data $end
$var reg 2 I byte_offset [1:0] $end
$upscope $end
$upscope $end
$scope module proc $end
$var wire 1 ' clk $end
$var wire 32 J data_in [31:0] $end
$var wire 32 K instr_in [31:0] $end
$var wire 1 + reset $end
$var wire 32 L rs [31:0] $end
$var wire 32 M rd [31:0] $end
$var reg 1 N EX_en $end
$var reg 32 O EX_instr_reg [31:0] $end
$var reg 1 P EX_mem_en $end
$var reg 1 Q EX_reg_wr_en $end
$var reg 1 R EX_wb_en $end
$var reg 5 S EX_wr_sel [4:0] $end
$var reg 1 T ID_en $end
$var reg 32 U ID_instr_reg [31:0] $end
$var reg 1 V IF_en $end
$var reg 1 W ME_en $end
$var reg 32 X ME_instr_reg [31:0] $end
$var reg 1 Y ME_mem_en $end
$var reg 1 Z ME_reg_wr_en $end
$var reg 1 [ ME_wb_en $end
$var reg 32 \ ME_wr_reg [31:0] $end
$var reg 5 ] ME_wr_sel [4:0] $end
$var reg 1 ^ WB_en $end
$var reg 32 _ WB_instr_reg [31:0] $end
$var reg 1 ` WB_reg_wr_en $end
$var reg 1 a WB_wb_en $end
$var reg 32 b WB_wr_reg_data [31:0] $end
$var reg 5 c WB_wr_sel [4:0] $end
$var reg 1 d alu_en $end
$var reg 5 e alu_op [4:0] $end
$var reg 32 f alu_out [31:0] $end
$var reg 32 g data_addr [31:0] $end
$var reg 32 h data_out [31:0] $end
$var reg 1 # data_rd_wr $end
$var reg 1 i data_rw_en $end
$var reg 32 j instr_addr [31:0] $end
$var reg 32 k pc [31:0] $end
$var reg 5 l rd_sel [4:0] $end
$var reg 5 m rs_sel [4:0] $end
$var reg 1 n sign_extend_en $end
$scope module regs $end
$var wire 1 ' clk $end
$var wire 5 o rd0_num [4:0] $end
$var wire 5 p rd1_num [4:0] $end
$var wire 32 q wr_data [31:0] $end
$var wire 1 ` wr_en $end
$var wire 5 r wr_num [4:0] $end
$var wire 32 s rd1_data [31:0] $end
$var wire 32 t rd0_data [31:0] $end
$upscope $end
$scope begin EX $end
$upscope $end
$scope begin ID $end
$upscope $end
$scope begin IF $end
$upscope $end
$scope begin ME $end
$upscope $end
$scope begin WB $end
$upscope $end
$upscope $end
$upscope $end
$enddefinitions $end
#0
$dumpvars
bx t
bx s
b11111 r
b0 q
bx p
bx o
xn
bx m
bx l
b10000000000000100000000000000000 k
b10000000000000100000000000000000 j
1i
bx h
b10000000000100100000000000000000 g
b0 f
b0 e
0d
b11111 c
b0 b
0a
1`
bx _
0^
bx ]
bx \
0[
0Z
0Y
bx X
0W
0V
bx U
0T
bx S
0R
0Q
0P
bx O
0N
bx M
bx L
bx K
bx J
bx I
bx H
bx G
bx F
bx E
b0 D
b0xxxxxxxxxxxxxxxxxxxxxxxxxxxxxx C
bx B
bx A
0@
b0 ?
b10000000000000100000000000000000 >
0=
bz <
b0 ;
bx :
bx 9
bx 8
bx 7
bx 6
b0 5
b0xxxxxxxxxxxxxxxxxxxxxxxxxxxxxx 4
bx 3
bx 2
01
b0 0
b10000000000100100000000000000000 /
bx .
0-
b0 ,
1+
b0 *
1)
b0 (
1'
b10000000000100100000000000000000 &
bx %
bx $
1#
b10000000000000100000000000000000 "
bx !
$end
#5
0'
#10
b10000000000100100000000000000000 b
b10000000000100100000000000000000 q
b11101 c
b11101 r
1V
b0 8
b0 7
b1000000000000000000 6
b1000000000000000000 4
b10000000000100100000000000000000 9
b0 2
b100100000000100000000000000001 !
b100100000000100000000000000001 B
b100100000000100000000000000001 K
b0 G
b0 F
b0 E
b0 C
b10000000000000100000000000000000 H
b0 A
1-
1=
0+
1'
#15
0'
#20
1T
b100100000000100000000000000001 U
1'
#25
0'
#30
b0 L
b0 s
1N
1R
b1 e
1d
1n
b0 m
b0 p
b10 S
b100100000000100000000000000001 O
1'
#35
0'
#40
b100100000100000000000000000010 !
b100100000100000000000000000010 B
b100100000100000000000000000010 K
b1 E
b1 C
b10000000000000100000000000000100 H
b10000000000000100000000000000100 "
b10000000000000100000000000000100 >
b10000000000000100000000000000100 j
b10000000000000100000000000000100 k
b1 \
1W
b100100000000100000000000000001 X
b10 ]
1[
b1 f
1'
#45
0'
#50
b100100000100010000000000000011 !
b100100000100010000000000000011 B
b100100000100010000000000000011 K
b10 E
b10 C
b10000000000000100000000000001000 H
b10000000000000100000000000001000 "
b10000000000000100000000000001000 >
b10000000000000100000000000001000 j
1^
b1 b
b1 q
b10 c
b10 r
1a
b100100000000100000000000000001 _
b10000000000000100000000000001000 k
b100100000100000000000000000010 U
1'
#55
0'
#60
b100100000100100000000000000100 !
b100100000100100000000000000100 B
b100100000100100000000000000100 K
b11 E
b11 C
b10000000000000100000000000001100 H
b10000000000000100000000000001100 "
b10000000000000100000000000001100 >
b10000000000000100000000000001100 j
b10000000000000100000000000001100 k
b10000 S
b100100000100000000000000000010 O
b100100000100010000000000000011 U
1'
#65
0'
#70
b10101111101000101111111111111100 !
b10101111101000101111111111111100 B
b10101111101000101111111111111100 K
b100 E
b100 C
b10000000000000100000000000010000 H
b10000000000000100000000000010000 "
b10000000000000100000000000010000 >
b10000000000000100000000000010000 j
b10000000000000100000000000010000 k
b10 \
b100100000100000000000000000010 X
b10000 ]
b10001 S
b100100000100010000000000000011 O
b100100000100100000000000000100 U
b10 f
1'
#75
0'
#80
b10001111101000111111111111111100 !
b10001111101000111111111111111100 B
b10001111101000111111111111111100 K
b101 E
b101 C
b10000000000000100000000000010100 H
b10000000000000100000000000010100 "
b10000000000000100000000000010100 >
b10000000000000100000000000010100 j
b10 b
b10 q
b10000 c
b10000 r
b100100000100000000000000000010 _
b10000000000000100000000000010100 k
b11 \
b100100000100010000000000000011 X
b10001 ]
b10010 S
b100100000100100000000000000100 O
b10101111101000101111111111111100 U
b11 f
1'
#85
0'
#90
b0 !
b0 B
b0 K
b110 E
b110 C
b10000000000000100000000000011000 H
b10000000000000100000000000011000 "
b10000000000000100000000000011000 >
b10000000000000100000000000011000 j
b1 M
b1 t
b10000000000100100000000000000000 L
b10000000000100100000000000000000 s
b11 b
b11 q
b10001 c
b10001 r
b100100000100010000000000000011 _
b10000000000000100000000000011000 k
b100 \
b100100000100100000000000000100 X
b10010 ]
1P
0R
b10 l
b10 o
b11101 m
b11101 p
b10 S
b10101111101000101111111111111100 O
b10001111101000111111111111111100 U
b100 f
1'
#95
0'
#100
b111 E
b111 C
b10000000000000100000000000011100 H
b10000000000000100000000000011100 "
b10000000000000100000000000011100 >
b10000000000000100000000000011100 j
b100 b
b100 q
b10010 c
b10010 r
b100100000100100000000000000100 _
b10000000000000100000000000011100 k
0#
b1 \
b10101111101000101111111111111100 X
b10 ]
1Y
0[
1R
b11 S
b10001111101000111111111111111100 O
b0 U
b1001111111111111111 6
b1001111111111111111 4
b10000000000100011111111111111100 9
b10000000000100011111111111111100 &
b10000000000100011111111111111100 /
b10000000000100011111111111111100 g
b1 %
b1 .
b1 h
b10000000000100011111111111111100 f
1'
#105
0'
#110
b1000 E
b1000 C
b10000000000000100000000000100000 H
b10000000000000100000000000100000 "
b10000000000000100000000000100000 >
b10000000000000100000000000100000 j
b1 $
b1 3
b1 J
b1001111111111111111 4
b0 L
b0 s
b1 b
b1 q
b10 c
b10 r
1a
b10101111101000101111111111111100 _
b10000000000000100000000000100000 k
1#
b10001111101000111111111111111100 X
b11 ]
1[
0R
0P
b1000 e
0d
b0 m
b0 p
b0 O
b0 S
b0 :
1'
#115
0'
#120
b11000100001000000100011 !
b11000100001000000100011 B
b11000100001000000100011 K
b1001 E
b1001 C
b10000000000000100000000000100100 H
b10000000000000100000000000100100 "
b10000000000000100000000000100100 >
b10000000000000100000000000100100 j
0a
b11 c
b11 r
b10001111101000111111111111111100 _
b10000000000000100000000000100100 k
b0 X
b0 ]
0Y
0[
1'
#125
0'
#130
b0 !
b0 B
b0 K
b1010 E
b1010 C
b10000000000000100000000000101000 H
b10000000000000100000000000101000 "
b10000000000000100000000000101000 >
b10000000000000100000000000101000 j
b0 M
b0 t
0`
b0 c
b0 r
b0 _
b10000000000000100000000000101000 k
1R
0n
b10 e
1d
b0 l
b0 o
b11000100001000000100011 U
1'
#135
0'
#140
b1011 E
b1011 C
b10000000000000100000000000101100 H
b10000000000000100000000000101100 "
b10000000000000100000000000101100 >
b10000000000000100000000000101100 j
b1 L
b1 s
b10000000000000100000000000101100 k
b0 \
b0 f
1[
0R
b1000 e
0d
b10 m
b10 p
b11000100001000000100011 O
b0 U
b10 S
1'
#145
0'
#150
b1100 E
b1100 C
b10000000000000100000000000110000 H
b10000000000000100000000000110000 "
b10000000000000100000000000110000 >
b10000000000000100000000000110000 j
b0 L
b0 s
b0 b
b0 q
1a
b10000000000000100000000000110000 k
b11000100001000000100011 X
b10 ]
0[
b0 m
b0 p
b0 O
b0 S
1'
#155
0'
#160
b1101 E
b1101 C
b10000000000000100000000000110100 H
b10000000000000100000000000110100 "
b10000000000000100000000000110100 >
b10000000000000100000000000110100 j
1`
b10 c
b10 r
0a
b11000100001000000100011 _
b10000000000000100000000000110100 k
b0 X
b0 ]
1'
#165
0'
#170
b10000010000000000000000000011 !
b10000010000000000000000000011 B
b10000010000000000000000000011 K
b1110 E
b1110 C
b10000000000000100000000000111000 H
b10000000000000100000000000111000 "
b10000000000000100000000000111000 >
b10000000000000100000000000111000 j
0`
b0 c
b0 r
b0 _
b10000000000000100000000000111000 k
1'
#175
0'
#180
b0 !
b0 B
b0 K
b1111 E
b1111 C
b10000000000000100000000000111100 H
b10000000000000100000000000111100 "
b10000000000000100000000000111100 >
b10000000000000100000000000111100 j
b10000000000000100000000000111100 k
b10000010000000000000000000011 U
1'
#185
0'
#190
b10000 E
b10000 C
b10000000000000100000000001000000 H
b10000000000000100000000001000000 "
b10000000000000100000000001000000 >
b10000000000000100000000001000000 j
b10000000000000100000000001000000 k
b10000 e
b10000010000000000000000000011 O
b0 U
1n
1d
b10 m
b10 p
1'
#195
0'
#200
b10001 E
b10001 C
b10000000000000100000000001000100 H
b10000000000000100000000001000100 "
b10000000000000100000000001000100 >
b10000000000000100000000001000100 j
b10000000000000100000000001000100 k
b10000010000000000000000000011 X
b1000 e
0d
b0 m
b0 p
b0 O
1'
#205
0'
#210
b11111000000000000000001000 !
b11111000000000000000001000 B
b11111000000000000000001000 K
b10010 E
b10010 C
b10000000000000100000000001001000 H
b10000000000000100000000001001000 "
b10000000000000100000000001001000 >
b10000000000000100000000001001000 j
b10000010000000000000000000011 _
b10000000000000100000000001001000 k
b0 X
1'
#215
0'
#220
bx !
bx B
bx K
b100000000000001000000000000001 E
b100000000000001000000000000001 C
b100 H
b100 "
b100 >
b100 j
b0 _
b0 e
b11111000000000000000001000 U
b100 k
1'
